Lab93_DatabaseSystem/__init__.py
Lab93_DatabaseSystem/__main__.py
Lab93_DatabaseSystem-0.0.1.dist-info/METADATA
Lab93_DatabaseSystem-0.0.1.dist-info/WHEEL
Lab93_DatabaseSystem-0.0.1.dist-info/top_level.txt
Lab93_DatabaseSystem-0.0.1.dist-info/RECORD
