Metadata-Version: 2.1
Name: Lab93-DatabaseSystem
Version: 0.0.1
Summary: A tool for maintaining the lab database.
Author-email: Guyyatsu Hikikomori <hunter@guyyatsu.me>
Project-URL: Homepage, https://github.com/Lab-93/Database-System
Project-URL: Bug Tracker, https://github.com/Lab-93/Database-System/issues
Classifier: Programming Language :: Python :: 3
Classifier: License :: OSI Approved :: MIT License
Classifier: Operating System :: OS Independent
Requires-Python: >=3.7
Requires-Dist: Lab93Cryptogram
